shellmcp/__init__.py
shellmcp/cli.py
shellmcp/generator.py
shellmcp/models.py
shellmcp/parser.py
shellmcp/template_utils.py
shellmcp/utils.py
shellmcp/configs/__init__.py
shellmcp/configs/basics.yml
shellmcp/templates/README.md.j2
shellmcp/templates/requirements.txt.j2
shellmcp/templates/server.py.j2
shellmcp-1.1.0.dist-info/licenses/LICENSE
shellmcp-1.1.0.dist-info/METADATA
shellmcp-1.1.0.dist-info/WHEEL
shellmcp-1.1.0.dist-info/entry_points.txt
shellmcp-1.1.0.dist-info/top_level.txt
shellmcp-1.1.0.dist-info/RECORD
